psmi/__init__.py
psmi/auto_psmi.py
psmi-0.2.0.dist-info/licenses/LICENSE
psmi-0.2.0.dist-info/METADATA
psmi-0.2.0.dist-info/WHEEL
psmi-0.2.0.dist-info/top_level.txt
psmi-0.2.0.dist-info/RECORD
