Metadata-Version: 2.4
Name: psmi
Version: 0.2.0
Summary: An implementation of Pointwise Sliced Mutual Information (PSMI) for machine learning
Author-email: Jérémie Dentan <65963192+DentanJeremie@users.noreply.github.com>
License: LGPL-3
Project-URL: Homepage, https://github.com/orailix/psmi
Project-URL: Issues, https://github.com/orailix/psmi/issues
Classifier: Programming Language :: Python :: 3
Classifier: License :: OSI Approved :: GNU Lesser General Public License v3 (LGPLv3)
Classifier: Operating System :: OS Independent
Requires-Python: >=3.8
License-File: LICENSE
Requires-Dist: numpy>=1.18
Dynamic: license-file
